examples/function_examples/__init__.py
examples/function_examples/add_trial_events.py
examples/function_examples/add_trial_events2.py
examples/function_examples/bpod_info.py
examples/function_examples/manual_override.py
examples/function_examples/modules.py
examples/function_examples/serial_messages.py
examples/function_examples/test_soft_codes.py
examples/function_examples/trials_time.py
pybpodapi/__init__.py
pybpodapi/session.py
pybpodapi/settings.py
pybpodapi/bpod/__init__.py
pybpodapi/bpod/bpod_base.py
pybpodapi/bpod/bpod_com_protocol.py
pybpodapi/bpod/bpod_com_protocol_modules.py
pybpodapi/bpod/bpod_io.py
pybpodapi/bpod/non_blockingsocketreceive.py
pybpodapi/bpod/non_blockingstreamreader.py
pybpodapi/bpod/hardware/__init__.py
pybpodapi/bpod/hardware/channels.py
pybpodapi/bpod/hardware/hardware.py
pybpodapi/bpod/hardware/events/__init__.py
pybpodapi/bpod/hardware/events/base_eventname.py
pybpodapi/bpod/hardware/events/bpod0_7_5_fw9.py
pybpodapi/bpod/hardware/events/bpod0_7_9_fw13.py
pybpodapi/bpod/hardware/events/bpod0_7_9_fw20.py
pybpodapi/bpod/hardware/input_channels/__init__.py
pybpodapi/bpod/hardware/input_channels/bpod0_7_5_fw9.py
pybpodapi/bpod/hardware/input_channels/bpod0_7_9_fw13.py
pybpodapi/bpod/hardware/output_channels/__init__.py
pybpodapi/bpod/hardware/output_channels/bpod0_7_5_fw9.py
pybpodapi/bpod/hardware/output_channels/bpod0_7_9_fw13.py
pybpodapi/bpod/hardware/output_channels/bpod0_7_9_fw20.py
pybpodapi/bpod_modules/__init__.py
pybpodapi/bpod_modules/bpod_module.py
pybpodapi/bpod_modules/bpod_modules.py
pybpodapi/com/__init__.py
pybpodapi/com/arcom.py
pybpodapi/com/stderr_buffer.py
pybpodapi/com/stdout_buffer.py
pybpodapi/com/messaging/__init__.py
pybpodapi/com/messaging/base_message.py
pybpodapi/com/messaging/debug.py
pybpodapi/com/messaging/end_trial.py
pybpodapi/com/messaging/error.py
pybpodapi/com/messaging/event_occurrence.py
pybpodapi/com/messaging/event_resume.py
pybpodapi/com/messaging/parser.py
pybpodapi/com/messaging/session_info.py
pybpod_api-1.8.2.dist-info/LICENSE.md
pybpod_api-1.8.2.dist-info/METADATA
pybpod_api-1.8.2.dist-info/WHEEL
pybpod_api-1.8.2.dist-info/top_level.txt
pybpod_api-1.8.2.dist-info/RECORD
