Metadata-Version: 1.0
Name: pybpod-api
Version: 1.8.2
Summary: BPod Python API
Home-page: https://github.com/pybpod/pybpod-api
Author: ['Joshua Sanders', 'Carlos Mão de Ferro', 'Ricardo Ribeiro', 'Luís Teixeira']
Author-email: joshua21@gmail.com, cajomferro@gmail.com, ricardojvr@gmail.com, micboucinha@gmail.com
License: MIT
Platform: UNKNOWN
